<annotation verified="yes">
                                    <folder>Annotation</folder>
                                    <filename>frame1350</filename>
                                    <path>/Users/nomanshafqat/Google Drive/Dataset/Aerial Labeling/Refined_output/JPEGImages/frame1350.jpg</path>
                                    <source>
                                        <database>Unknown</database>
                                    </source>
                                    <size>
                                        <width>435</width>
                                        <height>467</height>
                                        <depth>3</depth>
                                    </size>
                                    <segmented>0</segmented>
                                    <object>
                                            <name>V</name>
                                            <pose>Unspecified</pose>
                                            <bndbox>
                                                <xmin>207</xmin>
                                                <ymin>435</ymin>
                                                <xmax>241</xmax>
                                                <ymax>451</ymax>
                                            </bndbox>
                                    </object>
                                    
                                    <object>
                                            <name>V</name>
                                            <pose>Unspecified</pose>
                                            <bndbox>
                                                <xmin>118</xmin>
                                                <ymin>438</ymin>
                                                <xmax>164</xmax>
                                                <ymax>458</ymax>
                                            </bndbox>
                                    </object>
                                    
                                    <object>
                                            <name>V</name>
                                            <pose>Unspecified</pose>
                                            <bndbox>
                                                <xmin>94</xmin>
                                                <ymin>372</ymin>
                                                <xmax>140</xmax>
                                                <ymax>395</ymax>
                                            </bndbox>
                                    </object>
                                    
                                    <object>
                                            <name>V</name>
                                            <pose>Unspecified</pose>
                                            <bndbox>
                                                <xmin>46</xmin>
                                                <ymin>398</ymin>
                                                <xmax>78</xmax>
                                                <ymax>413</ymax>
                                            </bndbox>
                                    </object>
                                    
                                    <object>
                                            <name>V</name>
                                            <pose>Unspecified</pose>
                                            <bndbox>
                                                <xmin>20</xmin>
                                                <ymin>277</ymin>
                                                <xmax>55</xmax>
                                                <ymax>297</ymax>
                                            </bndbox>
                                    </object>
                                    
                                    <object>
                                            <name>V</name>
                                            <pose>Unspecified</pose>
                                            <bndbox>
                                                <xmin>57</xmin>
                                                <ymin>261</ymin>
                                                <xmax>88</xmax>
                                                <ymax>275</ymax>
                                            </bndbox>
                                    </object>
                                    
                                    <object>
                                            <name>V</name>
                                            <pose>Unspecified</pose>
                                            <bndbox>
                                                <xmin>120</xmin>
                                                <ymin>275</ymin>
                                                <xmax>159</xmax>
                                                <ymax>291</ymax>
                                            </bndbox>
                                    </object>
                                    
                                    <object>
                                            <name>V</name>
                                            <pose>Unspecified</pose>
                                            <bndbox>
                                                <xmin>141</xmin>
                                                <ymin>245</ymin>
                                                <xmax>180</xmax>
                                                <ymax>262</ymax>
                                            </bndbox>
                                    </object>
                                    
                                    <object>
                                            <name>V</name>
                                            <pose>Unspecified</pose>
                                            <bndbox>
                                                <xmin>211</xmin>
                                                <ymin>232</ymin>
                                                <xmax>247</xmax>
                                                <ymax>247</ymax>
                                            </bndbox>
                                    </object>
                                    
                                    <object>
                                            <name>V</name>
                                            <pose>Unspecified</pose>
                                            <bndbox>
                                                <xmin>72</xmin>
                                                <ymin>181</ymin>
                                                <xmax>108</xmax>
                                                <ymax>201</ymax>
                                            </bndbox>
                                    </object>
                                    
                                    <object>
                                            <name>V</name>
                                            <pose>Unspecified</pose>
                                            <bndbox>
                                                <xmin>188</xmin>
                                                <ymin>173</ymin>
                                                <xmax>223</xmax>
                                                <ymax>188</ymax>
                                            </bndbox>
                                    </object>
                                    
                                    <object>
                                            <name>V</name>
                                            <pose>Unspecified</pose>
                                            <bndbox>
                                                <xmin>323</xmin>
                                                <ymin>163</ymin>
                                                <xmax>357</xmax>
                                                <ymax>180</ymax>
                                            </bndbox>
                                    </object>
                                    
                                    <object>
                                            <name>V</name>
                                            <pose>Unspecified</pose>
                                            <bndbox>
                                                <xmin>236</xmin>
                                                <ymin>149</ymin>
                                                <xmax>277</xmax>
                                                <ymax>168</ymax>
                                            </bndbox>
                                    </object>
                                    
                                    <object>
                                            <name>V</name>
                                            <pose>Unspecified</pose>
                                            <bndbox>
                                                <xmin>203</xmin>
                                                <ymin>92</ymin>
                                                <xmax>236</xmax>
                                                <ymax>111</ymax>
                                            </bndbox>
                                    </object>
                                    
                                    <object>
                                            <name>V</name>
                                            <pose>Unspecified</pose>
                                            <bndbox>
                                                <xmin>61</xmin>
                                                <ymin>26</ymin>
                                                <xmax>91</xmax>
                                                <ymax>46</ymax>
                                            </bndbox>
                                    </object>
                                    </annotation>